cloudflarectl/__init__.py
cloudflarectl/__main__.py
cloudflarectl/cli/__init__.py
cloudflarectl/cli/commands/user.py
cloudflarectl-0.1.0.dist-info/entry_points.txt
cloudflarectl-0.1.0.dist-info/LICENSE
cloudflarectl-0.1.0.dist-info/WHEEL
cloudflarectl-0.1.0.dist-info/METADATA
cloudflarectl-0.1.0.dist-info/RECORD
